rate_my_project/__init__.py
rate_my_project/__main__.py
rate_my_project/cli.py
rate_my_project/config.py
rate_my_project/dashboard.py
rate_my_project/metric.py
rate_my_project/report.py
rate_my_project/utils.py
rate_my_project/connectors/__init__.py
rate_my_project/connectors/confluenceclient.py
rate_my_project/connectors/httpclient.py
rate_my_project/connectors/jiraclient.py
rate_my_project/metrics/__init__.py
rate_my_project/metrics/status.py
rate_my_project/metrics/templates/report.jinja2
rate_my_project-1.2.0.dist-info/LICENSE
rate_my_project-1.2.0.dist-info/METADATA
rate_my_project-1.2.0.dist-info/WHEEL
rate_my_project-1.2.0.dist-info/entry_points.txt
rate_my_project-1.2.0.dist-info/top_level.txt
rate_my_project-1.2.0.dist-info/RECORD
