Metadata-Version: 2.1
Name: rate_my_project
Version: 1.2.0
Summary: Swiss knife tool for analyzing project efficiency
Home-page: https://github.com/cledouarec/rate-my-project
Author: Christophe Le Douarec
Author-email: ledouarec@gmail.com
License: Apache License 2.0
Keywords: team efficiency data visualization analysis
Classifier: Programming Language :: Python :: 3 :: Only
Classifier: License :: OSI Approved :: Apache Software License
Classifier: Operating System :: OS Independent
Classifier: Environment :: Console
Classifier: Topic :: Utilities
License-File: LICENSE
Requires-Dist: aiohttp
Requires-Dist: Click
Requires-Dist: dash[diskcache]
Requires-Dist: dash-bootstrap-components
Requires-Dist: dash-bootstrap-templates
Requires-Dist: inflection
Requires-Dist: Jinja2
Requires-Dist: kaleido
Requires-Dist: pandas
Requires-Dist: plotly
Requires-Dist: pydantic
Requires-Dist: pydantic-settings
Requires-Dist: python-dateutil
Requires-Dist: pyyaml
Provides-Extra: dev
Requires-Dist: black ; extra == 'dev'
Requires-Dist: coverage ; extra == 'dev'
Requires-Dist: pre-commit ; extra == 'dev'
Requires-Dist: pylint ; extra == 'dev'
Requires-Dist: pytest ; extra == 'dev'
Requires-Dist: pytest-cov ; extra == 'dev'
